yt_playlist_export/__init__.py
yt_playlist_export/__main__.py
yt_playlist_export/yt_playlist_export.py
yt_playlist_export-0.0.6.dist-info/METADATA
yt_playlist_export-0.0.6.dist-info/WHEEL
yt_playlist_export-0.0.6.dist-info/entry_points.txt
yt_playlist_export-0.0.6.dist-info/licenses/LICENSE
yt_playlist_export-0.0.6.dist-info/RECORD
