Metadata-Version: 2.4
Name: yt-playlist-export
Version: 0.0.6
Summary: yt-playlist-export is a tiny Python tool that allows to export private YouTube playlists, export YouTube's "Watch later" list and export YouTube "Liked videos"
Project-URL: Homepage, https://github.com/daydiff/yt-playlist-export
Project-URL: Issues, https://github.com/daydiff/yt-playlist-export/issues
Author-email: Aleksandr Tabakov <info@atabakoff.com>
License: This is free and unencumbered software released into the public domain.
License-File: LICENSE
Keywords: youtube,youtube-playlist,youtube-playlist-backup,youtube-playlist-export 
Classifier: License :: OSI Approved :: The Unlicense (Unlicense)
Classifier: Operating System :: OS Independent
Classifier: Programming Language :: Python :: 3
Requires-Python: >=3.8
Requires-Dist: yt-dlp
